thestage_core/__init__.py
thestage_core/config/__init__.py
thestage_core/entities/__init__.py
thestage_core/entities/config_entity.py
thestage_core/entities/enums/__init__.py
thestage_core/entities/enums/order_direction_type.py
thestage_core/entities/enums/shell_type.py
thestage_core/entities/enums/tail_output_type.py
thestage_core/entities/enums/yes_no_response.py
thestage_core/entities/file_item.py
thestage_core/exceptions/__init__.py
thestage_core/exceptions/auth_exception.py
thestage_core/exceptions/base_exception.py
thestage_core/exceptions/business_logic_exception.py
thestage_core/exceptions/config_exception.py
thestage_core/exceptions/file_system_exception.py
thestage_core/exceptions/http_error_exception.py
thestage_core/main.py
thestage_core/services/__init__.py
thestage_core/services/clients/__init__.py
thestage_core/services/clients/thestage_api/__init__.py
thestage_core/services/clients/thestage_api/api_client.py
thestage_core/services/clients/thestage_api/api_client_abstract.py
thestage_core/services/clients/thestage_api/dtos/__init__.py
thestage_core/services/clients/thestage_api/dtos/base_response.py
thestage_core/services/clients/thestage_api/dtos/enums/__init__.py
thestage_core/services/clients/thestage_api/dtos/enums/access_type.py
thestage_core/services/clients/thestage_api/dtos/enums/container_pending_action.py
thestage_core/services/clients/thestage_api/dtos/enums/container_status.py
thestage_core/services/clients/thestage_api/dtos/enums/cpu_type.py
thestage_core/services/clients/thestage_api/dtos/enums/currency_type.py
thestage_core/services/clients/thestage_api/dtos/enums/disk_type.py
thestage_core/services/clients/thestage_api/dtos/enums/drive_type.py
thestage_core/services/clients/thestage_api/dtos/enums/gpu_name.py
thestage_core/services/clients/thestage_api/dtos/enums/instance_type.py
thestage_core/services/clients/thestage_api/dtos/enums/location_region.py
thestage_core/services/clients/thestage_api/dtos/enums/power_status.py
thestage_core-0.0.16.dist-info/METADATA
thestage_core-0.0.16.dist-info/WHEEL
thestage_core-0.0.16.dist-info/RECORD
