Metadata-Version: 2.1
Name: thestage-core
Version: 0.0.16
Summary: 
Author: TheStage AI team
Author-email: hello@thestage.ai
Requires-Python: >=3.9,<=3.13
Classifier: Programming Language :: Python :: 3
Classifier: Programming Language :: Python :: 3.9
Classifier: Programming Language :: Python :: 3.10
Classifier: Programming Language :: Python :: 3.11
Classifier: Programming Language :: Python :: 3.12
Requires-Dist: pydantic (>=2.4.2,<3.0.0)
Requires-Dist: python-dotenv (>=1.0.0,<2.0.0)
Requires-Dist: python-gettext-translations (>=1.1.0,<2.0.0)
Requires-Dist: requests (>=2.31.0,<3.0.0)
